jobs_data_contracts/__init__.py
jobs_data_contracts/jobs/__init__.py
jobs_data_contracts/jobs/models.py
jobs_data_contracts/search/__init__.py
jobs_data_contracts/search/models.py
jobs_data_contracts-1.2.2.dist-info/licenses/LICENSE
jobs_data_contracts-1.2.2.dist-info/METADATA
jobs_data_contracts-1.2.2.dist-info/WHEEL
jobs_data_contracts-1.2.2.dist-info/top_level.txt
jobs_data_contracts-1.2.2.dist-info/RECORD
