Metadata-Version: 2.4
Name: jobs-data-contracts
Version: 1.2.2
Summary: Canonical data contracts and schemas for the CS Jobs Board solution - Python Pydantic models
Author: CS Jobs Board Team
License: MIT
Project-URL: Homepage, https://github.com/Cab-mark/Jobs-data-contracts
Project-URL: Repository, https://github.com/Cab-mark/Jobs-data-contracts
Keywords: jobs,data-contracts,pydantic,openapi,fastapi
Classifier: Development Status :: 4 - Beta
Classifier: Intended Audience :: Developers
Classifier: License :: OSI Approved :: MIT License
Classifier: Programming Language :: Python :: 3
Classifier: Programming Language :: Python :: 3.8
Classifier: Programming Language :: Python :: 3.9
Classifier: Programming Language :: Python :: 3.10
Classifier: Programming Language :: Python :: 3.11
Classifier: Programming Language :: Python :: 3.12
Requires-Python: >=3.8
License-File: LICENSE
Requires-Dist: pydantic>=2.0.0
Requires-Dist: email-validator>=2.0.0
Provides-Extra: dev
Requires-Dist: datamodel-code-generator[http]>=0.25.0; extra == "dev"
Requires-Dist: pytest>=7.0.0; extra == "dev"
Dynamic: license-file
